mightypy/__init__.py
mightypy/data_structures/__init__.py
mightypy/data_structures/_linked_list.py
mightypy/data_structures/_search.py
mightypy/data_structures/_tree.py
mightypy/make/__init__.py
mightypy/make/_dataset.py
mightypy/ml/__init__.py
mightypy/ml/_ensemble.py
mightypy/ml/_error_fxs.py
mightypy/ml/_linear.py
mightypy/ml/_recommender.py
mightypy/ml/_tree.py
mightypy/ml/_utils.py
mightypy/signal_processing/__init__.py
mightypy/signal_processing/_fft.py
mightypy/stats/__init__.py
mightypy/stats/_data_drift.py
mightypy/stats/_feature_importance.py
mightypy-0.0.11.dist-info/AUTHORS.rst
mightypy-0.0.11.dist-info/LICENSE.txt
mightypy-0.0.11.dist-info/METADATA
mightypy-0.0.11.dist-info/WHEEL
mightypy-0.0.11.dist-info/top_level.txt
mightypy-0.0.11.dist-info/RECORD
