Metadata-Version: 2.1
Name: mightypy
Version: 0.0.11
Summary: This package initially started with the idea of expanding mightiness of python with expermenting on data structures and machine learning algorithms
Author-email: Nishant Baheti <nishantbaheti.it19@gmail.com>
License: The MIT License (MIT)
Project-URL: Homepage, https://github.com/nishantbaheti/mightypy
Project-URL: Bug Reports, https://github.com/nishantbaheti/mightypy/issues
Project-URL: Source, https://github.com/nishantbaheti/mightypy/
Keywords: sample,setuptools,development
Classifier: Intended Audience :: Developers
Classifier: Topic :: Software Development :: Build Tools
Classifier: Programming Language :: Python :: 3
Classifier: Programming Language :: Python :: 3.8
Classifier: Programming Language :: Python :: 3.9
Classifier: Programming Language :: Python :: 3 :: Only
Classifier: Intended Audience :: Science/Research
Classifier: Intended Audience :: Developers
Classifier: Intended Audience :: Financial and Insurance Industry
Classifier: Intended Audience :: Healthcare Industry
Classifier: Intended Audience :: Information Technology
Requires-Python: >=3.8
License-File: LICENSE.txt
License-File: AUTHORS.rst
Requires-Dist: numpy ==1.26.2
Requires-Dist: pandas ==2.1.3
Requires-Dist: matplotlib >=3.5.1
Requires-Dist: tqdm ==4.66.4
Provides-Extra: dev
Provides-Extra: test
Requires-Dist: pytest ==7.4.3 ; extra == 'test'
Requires-Dist: pytest-cov ==4.1.0 ; extra == 'test'
